ShiftAdd_Multiplier/include/log2_func.vh
`ifndef UTILS_VH
`define UTILS_VH

// --------------------------------------------------------------------
// Função log2
// Retorna o número de bits necessários para representar um valor.
// Exemplo:
//   log2(16) = 4
//   log2(17) = 5
// --------------------------------------------------------------------
function integer log2;
    input integer value;
    integer tmp;
    begin
        tmp = value - 1;
        log2 = 0;
        while (tmp > 0) begin
            log2 = log2 + 1;
            tmp = tmp >> 1;
        end
    end
endfunction

`endif

ShiftAdd_Multiplier/FSM_ShiftAdd_Multiplier.v
`include "log2_func.vh"

module FSM_ShiftAdd_Multiplier #(parameter WIDTH = 4) (
    input clk,
    input rst,
    input start,
    input lsb,
    input [COUNT_DEPTH:0] count,
    output reg load,
    output reg shift,
    output reg add,
    output reg done,
    output reg ld_count
);

localparam MULT_LENGTH = WIDTH;
localparam COUNT_DEPTH = log2(WIDTH); 

localparam S0 = 2'b00;
localparam S1 = 2'b01;
localparam S2 = 2'b10;
localparam S3 = 2'b11;

reg [1:0] state;

reg nextLoad;
reg nextShift;
reg nextAdd;
reg [1:0] nextState;
reg nextDone;
reg nextLd_count;

    always @(posedge clk or posedge rst) begin
        if (rst) begin
            ld_count <= 0;
            load <= 0;
            shift <= 0;
            add <= 0;
            done <= 0;
            state <= S0;
            nextLd_count <= 0;
            nextLoad <= 0;
            nextShift <= 0;
            nextAdd <= 0;
            nextDone <= 0;
            nextState <= S0;
        end else begin
            ld_count <= nextLd_count;
            load <= nextLoad;
            shift <= nextShift;
            add <= nextAdd;
            state <= nextState;
            done <= nextDone;
        end
    end
    
    always @(*) begin
        case (state)
            S0: begin
                if (start) begin
                    nextState = S0;
                    nextLoad = 1;
                end else if (load) begin
                    nextState = S1;
                    nextLoad = 0;
                end else begin
                    nextState = state;
                    nextLoad = 0;
                end
            end

            S1: begin
                /* Enquanto ainda não deu shift, não pode determinar a condição de soma (lsb ainda não atualizou) */
                if (shift) begin
                    nextState = state;
                    nextShift = 0;
                end else begin
                    /* Conta número de iterações necessárias */
                    if (count < MULT_LENGTH) begin
                        /* Lê bit menos significativo e determina se soma ou não */
                        if (lsb == 1) begin
                            nextAdd = 1;
                        end else begin 
                            nextAdd = 0;
                        end
                        /* Vai pra fase de shift e manda contador incrementar */
                        nextState = S2;
                        nextShift = 0;
                        nextLd_count = 1;
                    end else begin
                        nextState = S3;
                        nextShift = 0;
                        nextAdd = 0;
                        nextLd_count = 0;
                    end
                end
            end

            S2: begin
                /* Envia sinal de shift */
                nextLd_count = 0;
                nextAdd = 0;
                nextShift = 1;
                nextState = S1;
            end

            S3: begin 
                /* Finaliza e volta ao primeiro estado */
                nextDone = 1;
                nextState = S0;
            end

            default:
                nextState = S0;
        endcase
    end

endmodule

ShiftAdd_Multiplier/Datapath_ShiftAdd_Multiplier.v
module DataPath_ShiftAdd_Multiplier #(parameter WIDTH = 4) (
    input clk,
    input rst,
    input [WIDTH - 1:0] multiplier,
    input [WIDTH - 1:0] multiplicand,
    input load,
    input shift,
    input add,
    output lsb,
    output reg [WIDTH * 2:0] product
);

    always @(posedge clk or posedge rst) begin
        if (rst) begin
            product <= 0;
        end else begin
            if (load)
                product[WIDTH - 1:0] <= multiplier;
            else if (shift)
                product <= product >> 1;
            else if (add)
                product[WIDTH * 2:WIDTH] = {1'b0, product [(WIDTH * 2) - 1:WIDTH]} + {1'b0, multiplicand};
            else 
                product <= product;
        end
    end

    assign lsb = product[0];
endmodule

ShiftAdd_Multiplier/Counter_ShiftAdd_Multiplier.v
`include "log2_func.vh"

module Counter_ShiftAdd_Multiplier #(parameter WIDTH = 4) (
    input clk,
    input rst,
    input ld_count,
    output reg [COUNT_DEPTH:0] count
);

    localparam COUNT_DEPTH = log2(WIDTH);

    wire [COUNT_DEPTH:0] nextCount;

    always @(posedge clk or posedge rst) begin
        if (rst) count <= 0;
        else count <= nextCount;
    end

    assign nextCount = (ld_count == 1) ? (count + 1) : count;


endmodule

ShiftAdd_Multiplier/ShiftAdd_Multiplier.v
`include "log2_func.vh"

module ShiftAdd_Multiplier #(parameter TOP_WIDTH = 4) (
    input clk,
    input rst,
    input [TOP_WIDTH - 1:0] multiplier,
    input [TOP_WIDTH - 1:0] multiplicand,
    input start,
    output [TOP_WIDTH * 2:0] product,
    output done
);

localparam COUNT_DEPTH = log2(TOP_WIDTH); 

reg shift;
reg [COUNT_DEPTH:0] count;
reg load;
reg add;
reg lsb;
reg ld_count;

Counter_ShiftAdd_Multiplier #(.WIDTH(TOP_WIDTH)) Counter(.clk(clk), .rst(rst), .ld_count(ld_count), .count(count)); 
DataPath_ShiftAdd_Multiplier #(.WIDTH(TOP_WIDTH)) Datapath(.clk(clk), .rst(rst), .multiplier(multiplier), .multiplicand(multiplicand), .load(load), .shift(shift), .add(add), .lsb(lsb), .product(product));
FSM_ShiftAdd_Multiplier #(.WIDTH(TOP_WIDTH)) Controller(.clk(clk), .rst(rst), .start(start), .lsb(lsb), .count(count), .load(load), .shift(shift), .add(add), .done(done), .ld_count(ld_count));
    

endmodule

ShiftAdd_Multiplier/ShiftAdd_Multiplier_tb.v
`timescale 1ns/1ns

module ShiftAdd_Multiplier_tb #(parameter WIDTH = 8) ();

    reg clk;
    reg rst;
    reg [WIDTH - 1:0] multiplier;
    reg [WIDTH - 1:0] multiplicand;
    reg start;
    wire [WIDTH * 2:0] product;
    wire done;

    ShiftAdd_Multiplier #(.TOP_WIDTH(WIDTH)) Multiplier(.clk(clk), .rst(rst), .multiplier(multiplier), .multiplicand(multiplicand), .start(start), .product(product), .done(done));

    initial begin
        clk = 0;
        forever #5 clk = ~clk;
    end

    initial begin
        $dumpfile("dump.vcd");
        $dumpvars(0, ShiftAdd_Multiplier_tb);
        $monitor("at %t: done = %b, product = %b, start = %b, rst = %b", $realtime, done, product, start, rst);
        multiplier = 8'b1110_0011;
        multiplicand = 8'b1111_0010;
        start = 0;
        rst = 1;
        #5;
        rst = 0;
        #5;
        start = 1;
        #5;
        start = 0;
        $display("start: %b", start);
        //while (!done) begin

        //end
        #1500;
        $display("result of %b x %b = %b (%d x %d = %d)", multiplier, multiplicand, product, multiplier, multiplicand, product);
        $finish;
    end

endmodule

dump.vcd
$date
	Tue Sep 16 14:25:22 2025
$end
$version
	Icarus Verilog
$end
$timescale
	1ns
$end
$scope module ShiftAdd_Multiplier_tb $end
$var wire 17 ! product [16:0] $end
$var wire 1 " done $end
$var reg 1 # clk $end
$var reg 8 $ multiplicand [7:0] $end
$var reg 8 % multiplier [7:0] $end
$var reg 1 & rst $end
$var reg 1 ' start $end
$scope module Multiplier $end
$var wire 1 # clk $end
$var wire 8 ( multiplicand [7:0] $end
$var wire 8 ) multiplier [7:0] $end
$var wire 1 & rst $end
$var wire 1 ' start $end
$var wire 1 * shift $end
$var wire 17 + product [16:0] $end
$var wire 1 , lsb $end
$var wire 1 - load $end
$var wire 1 . ld_count $end
$var wire 1 " done $end
$var wire 4 / count [3:0] $end
$var wire 1 0 add $end
$scope module Controller $end
$var wire 1 # clk $end
$var wire 1 & rst $end
$var wire 1 ' start $end
$var wire 1 , lsb $end
$var wire 4 1 count [3:0] $end
$var reg 1 0 add $end
$var reg 1 " done $end
$var reg 1 . ld_count $end
$var reg 1 - load $end
$var reg 1 2 nextAdd $end
$var reg 1 3 nextDone $end
$var reg 1 4 nextLd_count $end
$var reg 1 5 nextLoad $end
$var reg 1 6 nextShift $end
$var reg 2 7 nextState [1:0] $end
$var reg 1 * shift $end
$var reg 2 8 state [1:0] $end
$upscope $end
$scope module Counter $end
$var wire 1 # clk $end
$var wire 1 . ld_count $end
$var wire 1 & rst $end
$var wire 4 9 nextCount [3:0] $end
$var reg 4 : count [3:0] $end
$upscope $end
$scope module Datapath $end
$var wire 1 0 add $end
$var wire 1 # clk $end
$var wire 1 - load $end
$var wire 8 ; multiplicand [7:0] $end
$var wire 8 < multiplier [7:0] $end
$var wire 1 & rst $end
$var wire 1 * shift $end
$var wire 1 , lsb $end
$var reg 17 = product [16:0] $end
$upscope $end
$upscope $end
$upscope $end
$enddefinitions $end
#0
$dumpvars
b0 =
b11100011 <
b11110010 ;
b0 :
b0 9
b0 8
b0 7
06
05
04
03
02
b0 1
00
b0 /
0.
0-
0,
b0 +
0*
b11100011 )
b11110010 (
0'
1&
b11100011 %
b11110010 $
0#
0"
b0 !
$end
#5
0&
1#
#10
15
1'
0#
#15
b1 7
1-
05
0'
1#
#20
0#
#25
14
b10 7
12
1,
b1 8
0-
b11100011 !
b11100011 +
b11100011 =
1#
#30
0#
#35
b1 7
16
02
04
b1 9
b10 8
10
1.
1#
#40
0#
#45
06
b1 8
00
1*
0.
b1 /
b1 1
b1 :
b1111001011100011 !
b1111001011100011 +
b1111001011100011 =
1#
#50
0#
#55
14
b10 7
12
b111100101110001 !
b111100101110001 +
b111100101110001 =
0*
1#
#60
0#
#65
b1 7
16
02
04
b10 9
b10 8
10
1.
1#
#70
0#
#75
06
b10 /
b10 1
b10 :
b1 8
00
1*
0.
b10110101101110001 !
b10110101101110001 +
b10110101101110001 =
1#
#80
0#
#85
14
b10 7
0,
0*
b1011010110111000 !
b1011010110111000 +
b1011010110111000 =
1#
#90
0#
#95
b1 7
16
04
b11 9
b10 8
1.
1#
#100
0#
#105
06
b1 8
1*
0.
b11 /
b11 1
b11 :
1#
#110
0#
#115
14
b10 7
b101101011011100 !
b101101011011100 +
b101101011011100 =
0*
1#
#120
0#
#125
b1 7
16
04
b100 9
b10 8
1.
1#
#130
0#
#135
06
b100 /
b100 1
b100 :
b1 8
1*
0.
1#
#140
0#
#145
14
b10 7
0*
b10110101101110 !
b10110101101110 +
b10110101101110 =
1#
#150
0#
#155
b1 7
16
04
b101 9
b10 8
1.
1#
#160
0#
#165
06
b1 8
1*
0.
b101 /
b101 1
b101 :
1#
#170
0#
#175
12
1,
14
b10 7
b1011010110111 !
b1011010110111 +
b1011010110111 =
0*
1#
#180
0#
#185
b1 7
16
02
04
b110 9
b10 8
10
1.
1#
#190
0#
#195
06
b110 /
b110 1
b110 :
b1 8
00
1*
0.
b10000100010110111 !
b10000100010110111 +
b10000100010110111 =
1#
#200
0#
#205
14
b10 7
12
0*
b1000010001011011 !
b1000010001011011 +
b1000010001011011 =
1#
#210
0#
#215
b1 7
16
02
04
b111 9
b10 8
10
1.
1#
#220
0#
#225
06
b1 8
00
1*
0.
b111 /
b111 1
b111 :
b10111011001011011 !
b10111011001011011 +
b10111011001011011 =
1#
#230
0#
#235
14
b10 7
12
b1011101100101101 !
b1011101100101101 +
b1011101100101101 =
0*
1#
#240
0#
#245
b1 7
16
02
04
b1000 9
b10 8
10
1.
1#
#250
0#
#255
06
b1000 /
b1000 1
b1000 :
b1 8
00
1*
0.
b11010110100101101 !
b11010110100101101 +
b11010110100101101 =
1#
#260
0#
#265
b11 7
0,
0*
b1101011010010110 !
b1101011010010110 +
b1101011010010110 =
1#
#270
0#
#275
b0 7
13
b11 8
1#
#280
0#
#285
1"
b0 8
1#
