Blackjack/Blackjack.sv
// Code your design here
module Blackjack (
  input clk,
  input reset,
  input stay,
  input hit,
  output win,
  output lose,
  output tie,
  //output tb
  output wire wfirst_draw,
  output wire wsoma_terminada,
  output wire [2:0] wcurrent_state,
  output wire whit_reg,
  output wire [2:0] wnext_state,
  output wire [4 - 1:0] wdeck [52],
  output wire [1:0] wdraw,
  output wire [3:0] wcard,
  output wire [6:0] wdeck_pos,
  output wire [3:0] whand [11],
  output wire wplayer_or_dealer,
  output wire [5:0] wreg_soma [11],
  output wire whit_reg_press,
  output wire [5:0] wsoma,
  output wire [5:0] wsoma_dealer
);

/************\
|*Constantes*|
\************/

// número de cartas = 13 -> 4 bits
parameter CARD = 4;
//soma máxima = 30 -> 6 bits
parameter MAX_SUM = 6;

reg win_reg, lose_reg, tie_reg;

reg [2:0] current_state;
reg [2:0] next_state;
wire [MAX_SUM - 1:0] soma;
wire [MAX_SUM - 1:0] soma_dealer;
reg [MAX_SUM - 1:0] reg_soma [11];
reg [MAX_SUM - 1:0] reg_soma_dealer [11];
reg [CARD - 1:0] deck [52];
reg [CARD - 1:0] card;
reg [CARD - 1:0] out_hand_temp [11];

/* Pior caso: A A A A 2 2 2 2 3 3 X = 11 cartas */
reg [CARD - 1:0] hand [11];
reg [CARD - 1:0] hand_dealer [11];
integer hand_pos;
reg [1:0] draw;
reg first_draw;// = 1;
reg soma_terminada;// = 0;
reg player_or_dealer;

reg hit_reg;
reg hit_reg_press;
reg first_cards_completed;
reg drawing_cards;
reg stop_dealing;

reg [CARD - 1:0] valor;
wire[CARD - 1:0] out_hand [11];
wire[CARD - 1:0] out_hand_dealer [11];

integer i;
integer deck_pos;
integer out_hand_pos;

//estados
parameter [2:0] INICIO        = 3'b000;
parameter [2:0] FIRST_CARDS   = 3'b001;
parameter [2:0] HIT_CARD      = 3'b010;
parameter [2:0] DEALER_CARDS  = 3'b011;
parameter [2:0] FINALIZACAO   = 3'b100;

/* Cartas */
/* Aqui as cartas ainda não estão sendo atribuídas valor, mas uma identidade única */
/* Dessa forma, o jogo é capaz de informar ao player que carta ele tirou, e utilizar um decodificador pra saber qual valor a carta possui */
parameter [3:0] AS        = 4'b0001;
parameter [3:0] DOIS      = 4'b0010;
parameter [3:0] TRES      = 4'b0011;
parameter [3:0] QUATRO    = 4'b0100;
parameter [3:0] CINCO     = 4'b0101;
parameter [3:0] SEIS      = 4'b0110;
parameter [3:0] SETE      = 4'b0111;
parameter [3:0] OITO      = 4'b1000;
parameter [3:0] NOVE      = 4'b1001;
parameter [3:0] DEZ       = 4'b1010;
parameter [3:0] VALETE    = 4'b1011;
parameter [3:0] DAMA      = 4'b1100;
parameter [3:0] REI       = 4'b1101;


parameter PLAYER = 0;
parameter DEALER = 1;

/* Preenchimento de memória com as cartas */


always @(card) begin
  if (player_or_dealer === PLAYER) begin
    hand[hand_pos] = card;
  end else if (player_or_dealer === DEALER) begin
    hand_dealer[hand_pos] = card;
  end
  hand_pos = hand_pos + 1;
end


/* Retira a carta da memória */
always @(posedge clk) begin
  if (reset) begin
    first_draw <= 1;
    soma_terminada <= 0;
    hit_reg <= 0;
    hand_pos <= 0;
    drawing_cards <= 0;

    deck_pos = $urandom_range(0, 51);
    next_state = INICIO;
    for (i = 0; i < 52; i = i + 1) begin
      deck[i] = i % 13 + 1;
    end
  end
  if (current_state === FIRST_CARDS && first_draw) begin
    draw <= 2;
    first_draw <= 0;
  end
  else if (current_state === HIT_CARD && hit_reg === 1) begin
    draw <= 1;
  end
  else if (current_state == DEALER_CARDS ) begin
    draw <= draw + 1;
  end

  if (draw && !stop_dealing) begin
    drawing_cards <= 1;
    deck_pos <= $urandom_range(0, 51);
    /* Procura uma posição do deck com carta */
    if (deck[deck_pos] !== 0) begin
      /* Pega carta do deck*/
      card <= deck[deck_pos];
      /* Retira o valor da carta do deck */
      deck[deck_pos] <= 4'b0000;
      /* Diminui o contador de quantas cartas pegar de uma vez */
      draw <= draw - 1;
    end
  end
  else if (drawing_cards === 1 && draw === 0) begin
    drawing_cards <= 0;
    first_cards_completed <= 1;
  end
end

/* Decodificador + load registrador soma */
always @(*) begin

  if (player_or_dealer === PLAYER) begin
    for (i = 0; i < 12; i = i + 1) begin
      out_hand_temp[i] = hand[i];
    end
  end else if (player_or_dealer === DEALER) begin
    for (i = 0; i < 12; i = i + 1) begin
      out_hand_temp[i] = hand_dealer[i];
    end
  end

  for (out_hand_pos = 0; out_hand_pos < 11; out_hand_pos = out_hand_pos + 1) begin
    case (out_hand_temp[out_hand_pos])
      AS:     valor = 1;
      DOIS:   valor = 2;
      TRES:   valor = 3;
      QUATRO: valor = 4;
      CINCO:  valor = 5;
      SEIS:   valor = 6;
      SETE:   valor = 7;
      OITO:   valor = 8;
      NOVE:   valor = 9;
      DEZ:    valor = 10;
      VALETE: valor = 10;
      DAMA:   valor = 10;
      REI:    valor = 10;
      default: valor = 0;
    endcase
    if (player_or_dealer == PLAYER) begin
      reg_soma[out_hand_pos] = valor;
    end else if (player_or_dealer == DEALER) begin
      reg_soma_dealer[out_hand_pos] = valor;
    end
  end
end

/* Somador */
/*always @(stay or hit) begin
integer reg_soma_pos;
for (reg_soma_pos = 0; reg_soma_pos < 11; reg_soma_pos = reg_soma_pos + 1) begin
if (player_or_dealer === PLAYER) begin
soma = soma + reg_soma[reg_soma_pos];
end else if (player_or_dealer === DEALER) begin
soma_dealer = soma_dealer + reg_soma[reg_soma_pos];
end
soma_terminada = 1;
end
end*/

/* Atualização máquina de estados */
always @(posedge clk) begin
  current_state <= next_state;
end

/* controle do hit para durar um ciclo de clock */
always @(posedge clk) begin
  if (hit === 1 && hit_reg_press === 1) begin
    hit_reg <= 1;
    hit_reg_press <= 0;
  end
  else if (hit === 1 && hit_reg_press === 0) begin
    hit_reg <= 0;
  end
  else if (hit == 0) begin
    hit_reg <= 0;
    hit_reg_press <= 1;
  end
end


/* Máquina de estados */
always @(*) begin
  case (current_state)
    INICIO:	begin
      stop_dealing = 0;
      if (hit_reg) begin
        next_state = FIRST_CARDS;
      end
    end

    FIRST_CARDS:	begin
      player_or_dealer = PLAYER;
      if (first_cards_completed) begin
        next_state = HIT_CARD;
      end
    end

    HIT_CARD:	begin
      player_or_dealer = PLAYER;

      if (stay == 1 || soma == 21) begin
        hand_pos = 0;
        next_state = DEALER_CARDS;
      end

      if (soma > 21) begin
        stop_dealing = 1;
        hand_pos = 0;
        next_state = FINALIZACAO;
      end
    end

    DEALER_CARDS:	begin
      stop_dealing = 0;
      player_or_dealer = DEALER;   
      if (soma_dealer >= 17) begin
        stop_dealing = 1;
        next_state = FINALIZACAO;
      end
    end

    FINALIZACAO:	begin
      //comparar as duas somas
      if (soma > 21) begin
        //perdeu
        win_reg = 0;
        tie_reg = 0;
        lose_reg = 1;
      end
      else if (soma == soma_dealer) begin
        //empate
        win_reg = 0;
        tie_reg = 1;
        lose_reg = 0;
      end
      else if (soma > soma_dealer) begin
        //ganhou
        win_reg = 1;
        tie_reg = 0;
        lose_reg = 0;
      end
      else if (soma_dealer > 21) begin
        win_reg = 1;
        tie_reg = 0;
        lose_reg = 0;
      end
      else if (soma < soma_dealer) begin
        //perdeu
        win_reg = 0;
        tie_reg = 0;
        lose_reg = 1;
      end
      //display pro usuário
      //reset
    end

    default:
      next_state = INICIO;
  endcase
end

assign win = win_reg;
assign lose = lose_reg;
assign tie = tie_reg;
assign soma = reg_soma[0] + reg_soma[1] + reg_soma[2] + reg_soma[3] + reg_soma[4] + reg_soma[5] + reg_soma[6] + reg_soma[7] + reg_soma[8] + reg_soma[9] + reg_soma[10]; 
assign soma_dealer = reg_soma_dealer[0] + reg_soma_dealer[1] + reg_soma_dealer[2] + reg_soma_dealer[3] + reg_soma_dealer[4] + reg_soma_dealer[5] + reg_soma_dealer[6] + reg_soma_dealer[7] + reg_soma_dealer[8] + reg_soma_dealer[9] + reg_soma_dealer[10];
/*testbench wires*/
assign wfirst_draw = first_draw;
assign wsoma_terminada = soma_terminada;
assign wcurrent_state = current_state;
assign whit_reg = hit_reg;
assign wnext_state = next_state;
assign wdeck = deck;
assign wplayer_or_dealer = player_or_dealer;

assign wdraw = draw;
assign wcard = card;  
assign wdeck_pos = deck_pos;
assign whand = hand;
assign wreg_soma = reg_soma;
assign whit_reg_press = hit_reg_press;
assign wsoma = soma;
assign wsoma_dealer = soma_dealer;

endmodule

Blackjack/Blackjack_tb.sv
// Code your testbench here
// or browse Examples

module Blackjack_tb ();
  reg clk_tb;
  reg reset_tb;
  reg stay_tb;
  reg hit_tb;
  wire win_tb;
  wire lose_tb;
  wire tie_tb;
  //output tb
  wire wfirst_draw_tb;
  wire wsoma_terminada_tb;
  wire [2:0] wcurrent_state_tb;
  wire whit_reg_tb;
  wire [2:0] wnext_state_tb;
  wire [4 - 1:0] wdeck_tb [52];
  wire [1:0] wdraw_tb;
  wire [3:0] wcard_tb;
  wire [6:0] wdeck_pos_tb;
  wire [3:0] whand_tb [11];
  wire wplayer_or_dealer_tb;
  wire [5:0] wreg_soma_tb [11];
  wire whit_reg_press_tb;
  wire [5:0] wsoma_tb;
  wire [5:0] wsoma_dealer_tb;
  
  integer i;
  int unsigned seed;

  Blackjack DUT(clk_tb, reset_tb, stay_tb, hit_tb, win_tb, lose_tb, tie_tb, wfirst_draw_tb, wsoma_terminada_tb, wcurrent_state_tb, whit_reg_tb, wnext_state_tb, wdeck_tb, wdraw_tb, wcard_tb, wdeck_pos_tb, whand_tb, wplayer_or_dealer_tb, wreg_soma_tb, whit_reg_press_tb, wsoma_tb, wsoma_dealer_tb);
  
  initial begin
    clk_tb = 0;
    forever #3 clk_tb = ~clk_tb;
  end
  
  initial begin
    seed = 121;
    $urandom(seed);
    $dumpfile("dump.vcd");
    $dumpvars(0, Blackjack_tb);
    $monitor("at time %4t: current_state = %b, reset = %b, hit = %b, hit_reg = %b, next_state = %b, draw = %b, card = %b, deck_pos = %b, player_or_dealer = %b, hit_reg_press = %b, soma = %d, soma_dealer = %d, win = %b, lose = %b, tie = %b", $realtime, wcurrent_state_tb, reset_tb, hit_tb, whit_reg_tb, wnext_state_tb, wdraw_tb, wcard_tb, wdeck_pos_tb, wplayer_or_dealer_tb, whit_reg_press_tb, wsoma_tb, wsoma_dealer_tb, win_tb, lose_tb, tie_tb);
    hit_tb = 0;
    reset_tb = 0; #10;
    reset_tb = 1; #10;
    reset_tb = 0; #10;
    for (i = 0; i < 52; i = i + 1) begin
      $display ("deck: %b", wdeck_tb[i]);
    end
    hit_tb = 1; #100;
    hit_tb = 0; #10;
    #10;
    hit_tb = 1; #100;
    hit_tb = 0; #10;
    #10;
    stay_tb = 1;
    #100;
    for (i = 0; i < 11; i = i + 1) begin
      $display("hand: %b", whand_tb[i]);
    end
    for (i = 0; i < 11; i = i + 1) begin
      $display("reg_soma: %b", wreg_soma_tb[i]);
    end
    $stop;
  end
  
  
  
endmodule

dump.vcd
$date
	Wed Aug 06 19:37:55 2025
$end
$version
	Icarus Verilog
$end
$timescale
	1s
$end
$scope module Blackjack_tb $end
$var wire 1 ! wsoma_terminada_tb $end
$var wire 6 " wsoma_tb [5:0] $end
$var wire 6 # wsoma_dealer_tb [5:0] $end
$var wire 1 $ wplayer_or_dealer_tb $end
$var wire 3 % wnext_state_tb [2:0] $end
$var wire 1 & win_tb $end
$var wire 1 ' whit_reg_tb $end
$var wire 1 ( whit_reg_press_tb $end
$var wire 1 ) wfirst_draw_tb $end
$var wire 2 * wdraw_tb [1:0] $end
$var wire 7 + wdeck_pos_tb [6:0] $end
$var wire 3 , wcurrent_state_tb [2:0] $end
$var wire 4 - wcard_tb [3:0] $end
$var wire 1 . tie_tb $end
$var wire 1 / lose_tb $end
$var reg 1 0 clk_tb $end
$var reg 1 1 hit_tb $end
$var reg 1 2 reset_tb $end
$var reg 1 3 stay_tb $end
$var integer 32 4 i [31:0] $end
$var reg 32 5 seed [31:0] $end
$scope module DUT $end
$var wire 1 0 clk $end
$var wire 1 1 hit $end
$var wire 1 / lose $end
$var wire 1 2 reset $end
$var wire 1 3 stay $end
$var wire 1 . tie $end
$var wire 4 6 wcard [3:0] $end
$var wire 3 7 wcurrent_state [2:0] $end
$var wire 2 8 wdraw [1:0] $end
$var wire 1 ) wfirst_draw $end
$var wire 1 ' whit_reg $end
$var wire 1 ( whit_reg_press $end
$var wire 1 & win $end
$var wire 3 9 wnext_state [2:0] $end
$var wire 1 $ wplayer_or_dealer $end
$var wire 6 : wsoma [5:0] $end
$var wire 6 ; wsoma_dealer [5:0] $end
$var wire 1 ! wsoma_terminada $end
$var wire 7 < wdeck_pos [6:0] $end
$var wire 6 = soma_dealer [5:0] $end
$var wire 6 > soma [5:0] $end
$var parameter 4 ? AS $end
$var parameter 32 @ CARD $end
$var parameter 4 A CINCO $end
$var parameter 4 B DAMA $end
$var parameter 32 C DEALER $end
$var parameter 3 D DEALER_CARDS $end
$var parameter 4 E DEZ $end
$var parameter 4 F DOIS $end
$var parameter 3 G FINALIZACAO $end
$var parameter 3 H FIRST_CARDS $end
$var parameter 3 I HIT_CARD $end
$var parameter 3 J INICIO $end
$var parameter 32 K MAX_SUM $end
$var parameter 4 L NOVE $end
$var parameter 4 M OITO $end
$var parameter 32 N PLAYER $end
$var parameter 4 O QUATRO $end
$var parameter 4 P REI $end
$var parameter 4 Q SEIS $end
$var parameter 4 R SETE $end
$var parameter 4 S TRES $end
$var parameter 4 T VALETE $end
$var reg 4 U card [3:0] $end
$var reg 3 V current_state [2:0] $end
$var reg 2 W draw [1:0] $end
$var reg 1 X drawing_cards $end
$var reg 1 Y first_cards_completed $end
$var reg 1 Z first_draw $end
$var reg 1 [ hit_reg $end
$var reg 1 \ hit_reg_press $end
$var reg 1 ] lose_reg $end
$var reg 3 ^ next_state [2:0] $end
$var reg 1 _ player_or_dealer $end
$var reg 1 ` soma_terminada $end
$var reg 1 a stop_dealing $end
$var reg 1 b tie_reg $end
$var reg 4 c valor [3:0] $end
$var reg 1 d win_reg $end
$var integer 32 e deck_pos [31:0] $end
$var integer 32 f hand_pos [31:0] $end
$var integer 32 g i [31:0] $end
$var integer 32 h out_hand_pos [31:0] $end
$upscope $end
$upscope $end
$enddefinitions $end
$comment Show the parameter values. $end
$dumpall
b1011 T
b11 S
b111 R
b110 Q
b1101 P
b100 O
b0 N
b1000 M
b1001 L
b110 K
b0 J
b10 I
b1 H
b100 G
b10 F
b1010 E
b11 D
b1 C
b1100 B
b101 A
b100 @
b1 ?
$end
#0
$dumpvars
bx h
bx g
bx f
bx e
xd
bx c
xb
xa
x`
x_
bx ^
x]
x\
x[
xZ
xY
xX
bx W
bx V
bx U
bx >
bx =
bx <
bx ;
bx :
bx 9
bx 8
bx 7
bx 6
b11111111000010111100110 5
bx 4
x3
02
01
00
x/
x.
bx -
bx ,
bx +
bx *
x)
x(
x'
x&
bx %
x$
bx #
bx "
x!
$end
#3
b0 %
b0 9
b0 ^
1(
1\
0'
0[
10
#6
00
#9
0a
b0 ,
b0 7
b0 V
10
#10
12
#12
00
#15
0X
b0 f
0!
0`
1)
1Z
b10100 +
b10100 <
b110100 g
b10100 e
10
#18
00
#20
02
#21
10
#24
00
#27
10
#30
00
11
b110100 4
#33
b1 %
b1 9
b1 ^
0(
0\
1'
1[
10
#36
00
#39
b0 "
b0 :
b0 >
b0 c
b1011 h
b1100 g
0$
0_
b1 ,
b1 7
b1 V
0'
0[
10
#42
00
#45
0)
0Z
b10 *
b10 8
b10 W
10
#48
00
#51
b1000 "
b1000 :
b1000 >
b0 c
b1011 h
b1100 g
b1 f
b10 +
b10 <
b1 *
b1 8
b1 W
b1000 -
b1000 6
b1000 U
b10 e
1X
10
#54
00
#57
b1011 "
b1011 :
b1011 >
b0 c
b1011 h
b1100 g
b10 f
b1010 +
b1010 <
b0 *
b0 8
b0 W
b11 -
b11 6
b11 U
b1010 e
10
#60
00
#63
b10 %
b10 9
b10 ^
1Y
0X
10
#66
00
#69
b10 ,
b10 7
b10 V
10
#72
00
#75
10
#78
00
#81
10
#84
00
#87
10
#90
00
#93
10
#96
00
#99
10
#102
00
#105
10
#108
00
#111
10
#114
00
#117
10
#120
00
#123
10
#126
00
#129
10
#130
01
#132
00
#135
1(
1\
10
#138
00
#141
10
#144
00
#147
10
#150
00
11
#153
0(
0\
1'
1[
10
#156
00
#159
b1 *
b1 8
b1 W
0'
0[
10
#162
00
#165
b11 %
b11 9
b11 ^
b10101 "
b10101 :
b10101 >
b0 c
b1011 h
b1100 g
b0 f
b100001 +
b100001 <
b0 *
b0 8
b0 W
b1011 -
b1011 6
b1011 U
b100001 e
1X
10
#168
00
#171
b0 #
b0 ;
b0 =
b1011 h
b1100 g
1$
1_
0X
b11 ,
b11 7
b11 V
10
#174
00
#177
b1 *
b1 8
b1 W
10
#180
00
#183
b1000 #
b1000 ;
b1000 =
b0 c
b1011 h
b1100 g
b1 f
b10000 +
b10000 <
b1000 -
b1000 6
b1000 U
b10000 e
1X
b0 *
b0 8
b0 W
10
#186
00
#189
0X
b1 *
b1 8
b1 W
10
#192
00
#195
b1100 #
b1100 ;
b1100 =
b0 c
b1011 h
b1100 g
b10 f
b10 +
b10 <
b100 -
b100 6
b100 U
b10 e
1X
b0 *
b0 8
b0 W
10
#198
00
#201
0X
b1 *
b1 8
b1 W
10
#204
00
#207
b111 +
b111 <
b111 e
1X
b10 *
b10 8
b10 W
10
#210
00
#213
b100 %
b100 9
b100 ^
1a
b10100 #
b10100 ;
b10100 =
b0 c
b1011 h
b1100 g
b11 f
b100000 +
b100000 <
b1000 -
b1000 6
b1000 U
b100000 e
b1 *
b1 8
b1 W
10
#216
00
#219
0/
0]
0.
0b
1&
1d
b10 *
b10 8
b10 W
b100 ,
b100 7
b100 V
10
#222
00
#225
10
#228
00
#231
10
#234
00
#237
10
#240
00
#243
10
#246
00
#249
10
#250
01
#252
00
#255
1(
1\
10
#258
00
#261
10
#264
00
#267
10
#270
00
13
